monstro/__init__.py
monstro/conf/__init__.py
monstro/conf/default.py
monstro/core/__init__.py
monstro/core/app.py
monstro/core/constants.py
monstro/core/exceptions.py
monstro/db/__init__.py
monstro/db/exceptions.py
monstro/db/expressions.py
monstro/db/fields.py
monstro/db/manager.py
monstro/db/model.py
monstro/db/proxy.py
monstro/db/queryset.py
monstro/db/router.py
monstro/db/migrations/__init__.py
monstro/db/migrations/models.py
monstro/forms/__init__.py
monstro/forms/exceptions.py
monstro/forms/fields.py
monstro/forms/forms.py
monstro/forms/widgets.py
monstro/management/__init__.py
monstro/management/commands/__init__.py
monstro/management/commands/db.py
monstro/management/commands/migrate.py
monstro/management/commands/new.py
monstro/management/commands/run.py
monstro/management/commands/shell.py
monstro/management/commands/test.py
monstro/management/templates/module/__init__.py
monstro/management/templates/module/handlers.py
monstro/management/templates/module/models.py
monstro/management/templates/module/urls.py
monstro/management/templates/module/views.py
monstro/management/templates/project/manage.py
monstro/management/templates/project/urls.py
monstro/management/templates/project/modules/__init__.py
monstro/management/templates/project/modules/urls.py
monstro/management/templates/project/modules/core/__init__.py
monstro/management/templates/project/modules/core/models.py
monstro/management/templates/project/modules/core/urls.py
monstro/management/templates/project/modules/core/views.py
monstro/management/templates/project/requirements/base.txt
monstro/management/templates/project/requirements/development.txt
monstro/management/templates/project/requirements/production.txt
monstro/management/templates/project/settings/__init__.py
monstro/management/templates/project/settings/base.py
monstro/management/templates/project/settings/development.py
monstro/management/templates/project/settings/production.py
monstro-4.2.4.dist-info/DESCRIPTION.rst
monstro-4.2.4.dist-info/METADATA
monstro-4.2.4.dist-info/RECORD
monstro-4.2.4.dist-info/WHEEL
monstro-4.2.4.dist-info/entry_points.txt
monstro-4.2.4.dist-info/metadata.json
monstro-4.2.4.dist-info/top_level.txt
