Metadata-Version: 2.0
Name: monstro
Version: 4.2.4
Summary: Web framework based on Tornado and MongoDB
Home-page: https://github.com/pyvim/monstro
Author: Vitalii Maslov
Author-email: me@pyvim.com
License: MIT
Download-URL: https://github.com/pyvim/monstro/tarball/master
Keywords: framework,web,tornado,mongodb,motor,asynchronous
Platform: UNKNOWN
Classifier: Intended Audience :: Developers
Classifier: Programming Language :: Python :: 3
Requires-Dist: motor
Requires-Dist: tornado
